aas_core3.0rc02-1.0.0rc3.data/data/LICENSE
aas_core3.0rc02-1.0.0rc3.data/data/README.rst
aas_core3_rc02/__init__.py
aas_core3_rc02/common.py
aas_core3_rc02/constants.py
aas_core3_rc02/jsonization.py
aas_core3_rc02/py.typed
aas_core3_rc02/stringification.py
aas_core3_rc02/types.py
aas_core3_rc02/verification.py
aas_core3_rc02/xmlization.py
aas_core3.0rc02-1.0.0rc3.dist-info/LICENSE
aas_core3.0rc02-1.0.0rc3.dist-info/METADATA
aas_core3.0rc02-1.0.0rc3.dist-info/WHEEL
aas_core3.0rc02-1.0.0rc3.dist-info/top_level.txt
aas_core3.0rc02-1.0.0rc3.dist-info/RECORD
