Metadata-Version: 2.1
Name: aas-core3.0rc02
Version: 1.0.0rc3
Summary: Manipulate, verify and de/serialize Asset Administration Shells.
Home-page: https://github.com/aas-core-works/aas-core3.0rc02-python
Author: Marko Ristin
Author-email: marko@ristin.ch
License: License :: OSI Approved :: MIT License
Keywords: asset administration shell sdk industry 4.0 industrie i4.0 industry iot iiot
Classifier: Development Status :: 5 - Production/Stable
Classifier: License :: OSI Approved :: MIT License
Classifier: Programming Language :: Python :: 3.6
Classifier: Programming Language :: Python :: 3.7
Classifier: Programming Language :: Python :: 3.8
Classifier: Programming Language :: Python :: 3.9
Classifier: Programming Language :: Python :: 3.10
Classifier: Programming Language :: Python :: 3.11
License-File: LICENSE
